write_read_file/LICENSE
write_read_file/README.MD
write_read_file/__init__.py
write_read_file/requirements.txt
write_read_file/thirdparty.json
write_read_file-0.10.dist-info/LICENSE.rst
write_read_file-0.10.dist-info/METADATA
write_read_file-0.10.dist-info/WHEEL
write_read_file-0.10.dist-info/top_level.txt
write_read_file-0.10.dist-info/RECORD
